databricks/__init__.py
databricks/conftest.py
databricks/koalas/__init__.py
databricks/koalas/accessors.py
databricks/koalas/base.py
databricks/koalas/categorical.py
databricks/koalas/config.py
databricks/koalas/datetimes.py
databricks/koalas/exceptions.py
databricks/koalas/extensions.py
databricks/koalas/frame.py
databricks/koalas/generic.py
databricks/koalas/groupby.py
databricks/koalas/indexing.py
databricks/koalas/internal.py
databricks/koalas/ml.py
databricks/koalas/mlflow.py
databricks/koalas/namespace.py
databricks/koalas/numpy_compat.py
databricks/koalas/series.py
databricks/koalas/sql.py
databricks/koalas/strings.py
databricks/koalas/utils.py
databricks/koalas/version.py
databricks/koalas/window.py
databricks/koalas/indexes/__init__.py
databricks/koalas/indexes/base.py
databricks/koalas/indexes/category.py
databricks/koalas/indexes/datetimes.py
databricks/koalas/indexes/multi.py
databricks/koalas/indexes/numeric.py
databricks/koalas/missing/__init__.py
databricks/koalas/missing/common.py
databricks/koalas/missing/frame.py
databricks/koalas/missing/groupby.py
databricks/koalas/missing/indexes.py
databricks/koalas/missing/series.py
databricks/koalas/missing/window.py
databricks/koalas/plot/__init__.py
databricks/koalas/plot/core.py
databricks/koalas/plot/matplotlib.py
databricks/koalas/plot/plotly.py
databricks/koalas/spark/__init__.py
databricks/koalas/spark/accessors.py
databricks/koalas/spark/functions.py
databricks/koalas/spark/utils.py
databricks/koalas/typedef/__init__.py
databricks/koalas/typedef/string_typehints.py
databricks/koalas/typedef/typehints.py
databricks/koalas/usage_logging/__init__.py
databricks/koalas/usage_logging/usage_logger.py
koalas-1.8.2.dist-info/LICENSE
koalas-1.8.2.dist-info/METADATA
koalas-1.8.2.dist-info/WHEEL
koalas-1.8.2.dist-info/top_level.txt
koalas-1.8.2.dist-info/RECORD
