Metadata-Version: 2.1
Name: koalas
Version: 1.8.2
Summary: Koalas: pandas API on Apache Spark
Home-page: https://github.com/databricks/koalas
Author: Databricks
Author-email: koalas@databricks.com
License: http://www.apache.org/licenses/LICENSE-2.0
Project-URL: Bug Tracker, https://github.com/databricks/koalas/issues
Project-URL: Documentation, https://koalas.readthedocs.io/
Project-URL: Source Code, https://github.com/databricks/koalas
Platform: UNKNOWN
Classifier: Programming Language :: Python :: 3.5
Classifier: Programming Language :: Python :: 3.6
Classifier: Programming Language :: Python :: 3.7
Classifier: Programming Language :: Python :: 3.8
Classifier: Programming Language :: Python :: 3.9
Requires-Python: >=3.5,<3.10
License-File: LICENSE
Requires-Dist: pandas (>=0.23.2)
Requires-Dist: pyarrow (>=0.10)
Requires-Dist: numpy (>=1.14)
Provides-Extra: matplotlib
Requires-Dist: matplotlib (<3.3.0,>=3.0.0) ; extra == 'matplotlib'
Provides-Extra: mlflow
Requires-Dist: mlflow (>=1.0) ; extra == 'mlflow'
Provides-Extra: plotly
Requires-Dist: plotly (>=4.8) ; extra == 'plotly'
Provides-Extra: spark
Requires-Dist: pyspark (>=2.4.0) ; extra == 'spark'
